{
    "name": "closeapp",
    "solution": "closeapp.sln",
    "targetproject": "zzzDist",
    "configuration": "Release",
    "targets": [
        {
            "setoutdirforbuild": false,
            "outdir": "Release\\v143\\closeapp\\",
            "platform": "Win32"
        }
    ],
    "ShouldBeFiles": [
        "closeapp.exe",
        "closeapp.pdb",
        "closeappw.exe",
        "closeappw.pdb",
        "history.txt",
        "README.md",
        "LICENSE"
    ],
    "TotalFileCount": "exact",
    "archivedir": "C:\\Linkout\\",
    "remotedir": "https://ambiesoft.com/ffdav/uploads/closeapp/",
    "remotesha1": "https://ambiesoft.com/ffdav/uploads/getSha1.php?file=closeapp/{}",
    "ShouldNotBeFiles": [],
    "ShouldBeOneOfThem": [],
    "obtainverfrom": "history.txt",
    "obtainverregex": "\\d+\\.\\d+\\.\\d+"
}
